FULL ADDER/pa12.v
module fadder (A, B, Cin, Sum, Cout);
	input A, B;
	input Cin;
	output Sum;
	output Cout;
	wire t1,t2,t3;
	xor g1(Sum,A,B,Cin);
	and g2(t1,B,Cin);
	and g3(t2,A,Cin);
	and g4(t3,A,B);
	or g5(Cout,t1,t2,t3);
endmodule //fadder


module add_sub_4 (A, B, In, Res, Out);
	input  [3:0] A, B;
	input In;
	output [3:0] Res;
	output Out;

	wire[3:0] Re;
	wire[3:0] carry;
	wire cnew;
	xor g1(Re[0],B[0],In);
	xor g2(Re[1],B[1],In);
	xor g3(Re[2],B[2],In);
	xor g4(Re[3],B[3],In);

	assign cnew = In;
	fadder DUT1(A[0],Re[0],cnew,Res[0],carry[0]);
	fadder DUT2(A[1],Re[1],carry[0],Res[1],carry[1]);
	fadder DUT3(A[2],Re[2],carry[1],Res[2],carry[2]);
	fadder DUT4(A[3],Re[3],carry[2],Res[3],carry[3]);
	assign Out = carry[3];



endmodule

FULL ADDER/pa11_tb.v
module testbench;
	reg A,B,Cin;
	wire Sum,Cout;

	fadder DUT(A,B,Cin,Sum,Cout);

	initial
		begin

			$monitor("At time : ",$time," A=%b, B=%b, Cin=%b, Sum=%b, Cout=%b",A,B,Cin,Sum,Cout);
			$dumpfile("pa11.vcd");
			$dumpvars(0,testbench);
			#5 A=0;B=0;Cin=0;
			#5 A=0;B=0;Cin=1;
			#5 A=0;B=1;Cin=0;
			#5 A=0;B=1;Cin=1;

			#5 A=1;B=0;Cin=0;
			#5 A=1;B=0;Cin=1;
			#5 A=1;B=1;Cin=0;
			#5 A=1;B=1;Cin=1;

			#5 $finish;
		end
endmodule

FULL ADDER/pa11.vcd
$date
	Wed Sep 12 18:48:14 2018
$end
$version
	Icarus Verilog
$end
$timescale
	1s
$end
$scope module testbench $end
$var wire 1 ! Sum $end
$var wire 1 " Cout $end
$var reg 1 # A $end
$var reg 1 $ B $end
$var reg 1 % Cin $end
$scope module DUT $end
$var wire 1 # A $end
$var wire 1 $ B $end
$var wire 1 % Cin $end
$var wire 1 " Cout $end
$var wire 1 ! Sum $end
$var wire 1 & t1 $end
$var wire 1 ' t2 $end
$var wire 1 ( t3 $end
$upscope $end
$upscope $end
$enddefinitions $end
#0
$dumpvars
x(
x'
x&
x%
x$
x#
x"
x!
$end
#5
0"
0&
0!
0'
0(
0%
0$
0#
#10
1!
1%
#15
0%
1$
#20
1"
0!
1&
1%
#25
0"
0&
1!
0%
0$
1#
#30
1"
0!
1'
1%
#35
0'
1(
0%
1$
#40
1!
1&
1'
1%
