8 TO 1 MUX/pa22.v
module mux2x1 (in, sel, out);
	input [1:0] in;
	input sel;
	output out;

	assign out = in[sel];
endmodule


module mux8x1 (in, sel, out);
	input [7:0] in;
	input [2:0] sel;
	output out;

	wire[3:0] p1;
	wire[1:0] p2;

	mux2x1 DUT1(in[1:0],sel[0],p1[0]);
	mux2x1 DUT2(in[3:2],sel[0],p1[1]);
	mux2x1 DUT3(in[5:4],sel[0],p1[2]);
	mux2x1 DUT4(in[7:6],sel[0],p1[3]);

	mux2x1 DUT5(p1[1:0],sel[1],p2[0]);
	mux2x1 DUT6(p1[3:2],sel[1],p2[1]);

	mux2x1 DUT7(p2[1:0],sel[2],out);

endmodule

8 TO 1 MUX/pa22_tb.v
module testbench; 
	reg[7:0] in;
	reg[2:0] sel;
	wire out;
	mux8x1 DUT(in,sel,out);

	
	initial
		begin
			
			$monitor("At time: ",$time," in=%b, sel=%b, out=%b",in,sel,out);  // what is printed
			$dumpfile("pa21_tb.vcd");
			$dumpvars(0,testbench);

			#5 in=8'b01100110;sel=3'b000;
			#5 in=8'b01100110;sel=3'b001;
			#5 in=8'b01100110;sel=3'b010;
			#5 in=8'b01100110;sel=3'b011;
			#5 in=8'b01100110;sel=3'b100;
			#5 in=8'b00000000;sel=3'b101;
			#5 in=8'b01100110;sel=3'b110;
			#5 in=8'b01100110;sel=3'b111;
			#5 in=8'b00000001;sel=3'b000;
			#5 in=8'b00100010;sel=3'b001;
			#5 $finish;

		end
endmodule

8 TO 1 MUX/pa21_tb.vcd
$date
	Thu Sep 13 03:42:02 2018
$end
$version
	Icarus Verilog
$end
$timescale
	1s
$end
$scope module testbench $end
$var wire 1 ! out $end
$var reg 8 " in [7:0] $end
$var reg 3 # sel [2:0] $end
$scope module DUT $end
$var wire 8 $ in [7:0] $end
$var wire 3 % sel [2:0] $end
$var wire 2 & p2 [1:0] $end
$var wire 4 ' p1 [3:0] $end
$var wire 1 ! out $end
$scope module DUT1 $end
$var wire 2 ( in [1:0] $end
$var wire 1 ) sel $end
$var wire 1 * out $end
$upscope $end
$scope module DUT2 $end
$var wire 2 + in [1:0] $end
$var wire 1 , sel $end
$var wire 1 - out $end
$upscope $end
$scope module DUT3 $end
$var wire 2 . in [1:0] $end
$var wire 1 / sel $end
$var wire 1 0 out $end
$upscope $end
$scope module DUT4 $end
$var wire 2 1 in [1:0] $end
$var wire 1 2 sel $end
$var wire 1 3 out $end
$upscope $end
$scope module DUT5 $end
$var wire 2 4 in [1:0] $end
$var wire 1 5 sel $end
$var wire 1 6 out $end
$upscope $end
$scope module DUT6 $end
$var wire 2 7 in [1:0] $end
$var wire 1 8 sel $end
$var wire 1 9 out $end
$upscope $end
$scope module DUT7 $end
$var wire 2 : in [1:0] $end
$var wire 1 ; sel $end
$var wire 1 ! out $end
$upscope $end
$upscope $end
$upscope $end
$enddefinitions $end
#0
$dumpvars
x;
bx :
x9
x8
bx 7
x6
x5
bx 4
x3
x2
bx 1
x0
x/
bx .
x-
x,
bx +
x*
x)
bx (
bx '
bx &
bx %
bx $
bx #
bx "
x!
$end
#5
0!
06
b10 4
b0 &
b0 :
09
b10 7
0*
0)
1-
0,
00
0/
b1010 '
13
02
05
08
0;
b10 (
b1 +
b10 .
b1 1
b0 #
b0 %
b1100110 "
b1100110 $
#10
1!
16
b1 4
b11 &
b11 :
19
b1 7
1*
1)
0-
1,
10
1/
b101 '
03
12
b1 #
b1 %
#15
b10 4
b10 7
0*
0)
1-
0,
00
0/
b1010 '
13
02
1!
16
15
b11 &
b11 :
19
18
b10 #
b10 %
#20
0!
06
b1 4
b0 &
b0 :
09
b1 7
1*
1)
0-
1,
10
1/
b101 '
03
12
b11 #
b11 %
#25
b10 4
b10 7
0*
0)
1-
0,
00
0/
b1010 '
13
02
06
05
0!
b0 &
b0 :
09
08
1;
b100 #
b100 %
#30
b0 4
b0 7
1)
1,
1/
12
b0 (
0-
b0 +
b0 .
b0 '
03
b0 1
b101 #
b101 %
b0 "
b0 $
#35
16
b10 4
1!
b11 &
b11 :
19
b10 7
0)
1-
0,
0/
13
02
15
18
0*
b10 (
b1 +
b1010 '
00
b10 .
b1 1
b110 #
b110 %
b1100110 "
b1100110 $
#40
06
b1 4
0!
b0 &
b0 :
09
b1 7
1*
1)
0-
1,
10
1/
b101 '
03
12
b111 #
b111 %
#45
b0 7
0)
0,
0/
02
1!
16
05
b1 &
b1 :
09
08
0;
1*
b1 (
b0 +
b1 '
00
b0 .
b0 1
b0 #
b0 %
b1 "
b1 $
#50
b11 &
b11 :
19
b1 7
1)
1,
10
1/
12
b101 '
1*
b10 (
b10 .
b1 #
b1 %
b100010 "
b100010 $
